AUTHORS.rst
CONTRIBUTING.rst
HISTORY.rst
LICENSE
MANIFEST.in
README.rst
setup.cfg
setup.py
docs/Makefile
docs/authors.rst
docs/conf.py
docs/contributing.rst
docs/history.rst
docs/index.rst
docs/installation.rst
docs/make.bat
docs/readme.rst
docs/usage.rst
teacv/__init__.py
teacv/cli.py
teacv/teacv.py
teacv.egg-info/PKG-INFO
teacv.egg-info/SOURCES.txt
teacv.egg-info/dependency_links.txt
teacv.egg-info/entry_points.txt
teacv.egg-info/not-zip-safe
teacv.egg-info/requires.txt
teacv.egg-info/top_level.txt
tests/test_tea.py