Metadata-Version: 1.1
Name: teacv
Version: 0.1.0
Summary: teacv is a tool for extend Python OpenCV modules with custom filters written in C++.
Home-page: https://github.com/GudarJs/teacv
Author: Guzmán D. Darío
Author-email: guzman.d.dario@gmail.com
License: MIT license
Keywords: teacv
Platform: UNKNOWN
Classifier: Development Status :: 2 - Pre-Alpha
Classifier: Intended Audience :: Developers
Classifier: License :: OSI Approved :: MIT License
Classifier: Natural Language :: English
Classifier: Programming Language :: Python :: 3
Classifier: Programming Language :: Python :: 3.5
Classifier: Programming Language :: Python :: 3.6
